{"mode":"playing","challengeType":"synonyms","coordinate_system":"origin top-left, +x right, +y down","targetWord":"RAPIDO","correctWord":"LIGERO","wrongRemaining":19,"touchedCorrect":false,"fireModeActive":false,"fireModeMsLeft":0,"cameraReady":true,"pose":{"confidence":1,"joints":[{"kind":"head","x":130,"y":42,"r":14},{"kind":"leftWrist","x":64,"y":102,"r":14},{"kind":"rightWrist","x":196,"y":102,"r":14},{"kind":"torso","x":130,"y":98,"r":18}],"segments":[{"kind":"leftArm","ax":114,"ay":68,"bx":58,"by":96},{"kind":"rightArm","ax":146,"ay":68,"bx":202,"by":96},{"kind":"shoulders","ax":104,"ay":62,"bx":156,"by":62},{"kind":"torso","ax":130,"ay":60,"bx":130,"by":134}]},"progress":{"level":1,"score":0,"seeds":0,"waters":0,"harvests":0,"knowledge":0,"alivePlants":0},"background":{"url":"mindmapBackground.png","ready":true,"transitionActive":false},"powerup":{"text":"FUEGO","x":389,"y":278,"active":true},"fireballs":[],"activeWords":[{"text":"TRISTE","isCorrect":false,"x":280,"y":-57,"width":415,"height":125},{"text":"CHICO","isCorrect":false,"x":128,"y":-78,"width":373,"height":112},{"text":"BRILLANTE","isCorrect":false,"x":248,"y":-215,"width":595,"height":179},{"text":"ALTO","isCorrect":false,"x":37,"y":-231,"width":337,"height":104},{"text":"INFANTE","isCorrect":false,"x":130,"y":-387,"width":488,"height":146},{"text":"LIGERO","isCorrect":true,"x":641,"y":-564,"width":416,"height":125},{"text":"MINIMO","isCorrect":false,"x":363,"y":-566,"width":431,"height":129},{"text":"TAREA","isCorrect":false,"x":361,"y":-674,"width":394,"height":118},{"text":"GRANDE","isCorrect":false,"x":165,"y":-763,"width":463,"height":139},{"text":"OSCURO","isCorrect":false,"x":84,"y":-824,"width":463,"height":139},{"text":"PEQUENO","isCorrect":false,"x":15,"y":-898,"width":523,"height":157},{"text":"IMPURO","isCorrect":false,"x":170,"y":-1025,"width":436,"height":131},{"text":"CASA","isCorrect":false,"x":427,"y":-995,"width":354,"height":106},{"text":"FLORES","isCorrect":false,"x":596,"y":-1161,"width":450,"height":135},{"text":"VIEJO","isCorrect":false,"x":204,"y":-1340,"width":356,"height":107},{"text":"FUERTE","isCorrect":false,"x":124,"y":-1443,"width":442,"height":133},{"text":"NINO","isCorrect":false,"x":42,"y":-1365,"width":323,"height":104},{"text":"BAJO","isCorrect":false,"x":111,"y":-1504,"width":342,"height":104},{"text":"BIBLIOTECA","isCorrect":false,"x":401,"y":-1654,"width":629,"height":189},{"text":"ENEMIGO","isCorrect":false,"x":345,"y":-1741,"width":503,"height":151}]}